{
  "40724": [
    "src/runtime",
    "src/cmd/compile/internal/arm",
    "src/cmd/compile/internal/ssa",
    "src/cmd/link/internal/loadpe",
    "src/cmd/compile/internal/wasm",
    "src/cmd/compile/internal/ssagen",
    "src/cmd/link/internal/ld",
    "src/cmd/compile/internal/liveness",
    "src/cmd/compile/internal/gc",
    "src/cmd/compile/internal/typecheck",
    "src/math",
    "src/cmd/compile/internal/mips64",
    "test/codegen",
    "src/cmd/cgo",
    "src/cmd/compile/internal/test",
    "src/cmd/compile/internal/ppc64",
    "src/cmd/internal/obj/wasm",
    "src/cmd/asm/internal/asm",
    "src/cmd/link/internal/loadxcoff",
    "src/reflect",
    "src/cmd/link/internal/loader",
    "src/runtime/race",
    "src/internal/bytealg",
    "src/cmd/compile/internal/riscv64",
    "src/cmd/compile/internal/walk",
    "src/cmd/link/internal/loadmacho",
    "src/runtime/cgo",
    "src/cmd/compile/internal/abi",
    "src/cmd/compile/internal/base",
    "src/internal/abi",
    "src/cmd/vendor/golang.org/x/tools/go/analysis/passes/asmdecl",
    "src/cmd/internal/objabi",
    "src/cmd/internal/obj",
    "src/cmd/compile/internal/x86",
    "src/cmd/compile/internal/s390x",
    "src/cmd/compile/internal/objw",
    "src/cmd/compile/internal/ir",
    "src/cmd/compile/internal/amd64",
    "src/cmd/compile/internal/mips",
    "src/cmd/compile/internal/types",
    "src/internal/abi/testdata",
    "src/cmd/internal/obj/x86"
  ],
  "47781": [
    "src/cmd/cgo",
    "src/go/types",
    "src/go/printer",
    "src/go/parser",
    "src/go/ast"
  ],
  "51572": [
    "src/cmd/go",
    "src/syscall",
    "src/cmd/dist",
    "src/go/build",
    "src/os/exec/internal/fdtest",
    "src/os",
    "src/runtime/pprof",
    "src/cmd/go/internal/help",
    "src/time",
    "src/crypto/tls",
    "src/path/filepath",
    "src/runtime",
    "src/mime",
    "src/os/user",
    "src/net",
    "src/internal/testenv",
    "src/runtime/cgo",
    "src/cmd/go/internal/base",
    "src/os/exec",
    "src/os/signal",
    "src/cmd/go/internal/modload",
    "src/cmd/go/testdata/script",
    "src/internal/syscall/unix",
    "src/internal/poll",
    "src/net/internal/socktest",
    "src/archive/tar"
  ],
  "44853": [
    "src/cmd/compile/internal/pkginit",
    "src/cmd/go/testdata/script",
    "src/runtime",
    "src/cmd/go/internal/work",
    "src/cmd/compile/internal/base",
    "src/cmd/go/internal/cfg",
    "src/cmd/compile/internal/ir",
    "src/cmd/compile/internal/noder",
    "src/cmd/link",
    "src/runtime/asan",
    "src/cmd/go/internal/load",
    "src/cmd/compile/internal/ssagen",
    "src/cmd/link/internal/ld",
    "src/cmd/compile/internal/gc",
    "src/cmd/compile"
  ],
  "46742": [
    "doc",
    "src/unsafe",
    "test",
    "src/runtime/testdata/testprog",
    "src/runtime",
    "src/cmd/compile/internal/typecheck",
    "src/cmd/compile/internal/walk"
  ],
  "51082": [
    "src/encoding/binary",
    "src/cmd/internal/test2json",
    "src/log/syslog",
    "src/hash/maphash",
    "src/net/http/cgi",
    "src/cmd/internal/src",
    "src/net",
    "src/encoding/gob",
    "src/cmd/compile/internal/ssagen",
    "src/sync",
    "src/embed",
    "src/testing/quick",
    "src/context",
    "src/cmd/compile/internal/abi",
    "src/cmd/compile/internal/liveness",
    "src/cmd/internal/obj/riscv",
    "src/cmd/go/internal/str",
    "src/debug/dwarf",
    "src/testing",
    "src/cmd/internal/gcprog",
    "src/math",
    "src/cmd/compile/internal/inline",
    "src/go/internal/gccgoimporter",
    "src/go/ast",
    "src/html/template",
    "src/hash/adler32",
    "src/net/http/cookiejar",
    "src/cmd/go/internal/generate",
    "src/cmd/cgo",
    "src/crypto/x509/pkix",
    "src/net/http/pprof",
    "src/cmd/internal/obj",
    "src/cmd/asm/internal/asm",
    "src/encoding/pem",
    "src/path",
    "src/sync/atomic",
    "src/reflect",
    "src/cmd/link/internal/loader",
    "src/cmd/internal/goobj",
    "src/cmd/go/internal/test",
    "src/crypto/rsa",
    "src/hash/crc32",
    "src/internal/reflectlite",
    "misc/ios",
    "src/internal/poll",
    "src/cmd/compile/internal/walk",
    "src/cmd/link/internal/sym",
    "src/unicode",
    "src/cmd/fix",
    "src/go/doc/comment/testdata",
    "src/cmd/link/internal/s390x",
    "src/internal/goarch",
    "src/compress/flate",
    "src/net/http",
    "src/runtime/cgo",
    "src/crypto",
    "src/text/template",
    "src/database/sql",
    "src/crypto/x509",
    "src/cmd/go/internal/modload",
    "src/cmd/go/internal/modget",
    "src/cmd/go/internal/work",
    "src/archive/tar",
    "src/runtime/testdata/testprogcgo",
    "src/internal/txtar",
    "src/cmd/go",
    "src/runtime/trace",
    "src/go/doc/comment",
    "src/cmd/compile/internal/noder",
    "src/syscall",
    "src/cmd/internal/objabi",
    "src/cmd/dist",
    "src/cmd/link/internal/benchmark",
    "src/go/build",
    "src/encoding/json",
    "src/cmd/internal/bio",
    "src/cmd/asm",
    "src/cmd/compile/internal/types2",
    "misc/cgo/gmp",
    "src/cmd/go/internal/imports",
    "src/go/doc/testdata/pkgdoc",
    "src/image/jpeg",
    "src/debug/gosym",
    "src/cmd/internal/obj/x86",
    "src/unsafe",
    "src/go/constant",
    "src/cmd/link",
    "src/mime/multipart",
    "src/cmd/compile/internal/reflectdata",
    "src/cmd/compile/internal/ssa",
    "src/image/png",
    "src/internal/fmtsort",
    "src/syscall/js",
    "src/strings",
    "src/strconv",
    "src/time/tzdata",
    "src/regexp",
    "src/internal/nettrace",
    "src/encoding/xml",
    "src/cmd/compile/internal/x86",
    "src/os",
    "src/cmd/compile/internal/s390x",
    "src/crypto/x509/internal/macos",
    "src/net/http/httptest",
    "src/runtime/pprof",
    "src/cmd/go/internal/load",
    "src/cmd/compile/internal/syntax",
    "src/net/rpc",
    "src/net/smtp",
    "src/runtime/debug",
    "src/internal/goos",
    "src/cmd/link/internal/ld",
    "src/net/textproto",
    "src/cmd/compile/internal/ir",
    "src/fmt",
    "src/go/printer",
    "src/builtin",
    "src/go/printer/testdata",
    "src/time",
    "src/net/mail",
    "src/cmd/compile/internal/typecheck",
    "src/cmd/cover",
    "src/log",
    "src/math/big",
    "src/database/sql/driver",
    "src/text/template/parse",
    "src/cmd/compile/internal/amd64",
    "src/plugin",
    "src/regexp/syntax",
    "src/cmd/test2json",
    "src/cmd/compile/internal/pkginit",
    "src/crypto/tls",
    "src/cmd/compile/internal/types",
    "src/cmd/compile/internal/test",
    "src/image",
    "src/cmd/doc",
    "src/cmd/compile/internal/test/testdata",
    "src/net/http/internal",
    "src/go/types",
    "src/math/rand",
    "src/path/filepath",
    "src/runtime",
    "src/go/doc",
    "src/net/netip",
    "src/cmd/addr2line",
    "src/net/url",
    "src/cmd/go/internal/lockedfile",
    "src/mime",
    "src/math/cmplx"
  ],
  "42537": [
    "src/net",
    "src/crypto/ecdsa",
    "src/text/template",
    "src/crypto/x509",
    "src/html/template",
    "src/cmd/go/internal/clean",
    "src/encoding/pem",
    "src/bytes",
    "src/cmd/vet",
    "test",
    "misc/ios",
    "src/encoding/asn1",
    "src/archive/zip",
    "src/strconv",
    "src/cmd/fix",
    "src/runtime/testdata/testprog",
    "src/net/http",
    "src/archive/tar",
    "src/go/build",
    "src/regexp/syntax",
    "src/encoding/json",
    "src/crypto/tls",
    "src/go/constant",
    "src/go/importer",
    "src/strings",
    "src/regexp",
    "src/encoding/xml",
    "src/os",
    "src/runtime/pprof",
    "src/cmd/go/internal/load",
    "src/net/smtp",
    "src/runtime/debug",
    "src/go/printer",
    "src/net/mail",
    "src/os/exec",
    "src/cmd/doc",
    "src/net/http/internal",
    "src/go/types",
    "src/go/doc",
    "src/net/url",
    "src/mime",
    "src/os/user",
    "src/net/http/cgi"
  ],
  "33232": [
    "src/runtime/race/testdata",
    "src/encoding/binary",
    "src/cmd/internal/test2json",
    "src/expvar",
    "src/internal/nettrace",
    "src/cmd/cover/testdata",
    "src/container/heap",
    "src/runtime/pprof",
    "src/debug/pe",
    "src/net/rpc",
    "src/container/ring",
    "src/net/smtp",
    "src/debug/macho",
    "src/testing/quick",
    "src/net/textproto",
    "src/cmd/go/internal/help",
    "src/internal/singleflight",
    "src/debug/dwarf",
    "src/net/http/httptrace",
    "src/fmt",
    "src/go/printer",
    "src/go/doc/testdata",
    "src/go/printer/testdata",
    "src/io/fs",
    "src/net/mail",
    "src/go/parser",
    "src/math/big",
    "src/go/format",
    "src/text/template/parse",
    "src/go/ast",
    "src/cmd/nm",
    "src/cmd/go/internal/base",
    "src/os/exec",
    "src/crypto/x509/pkix",
    "src/flag",
    "src/cmd/doc",
    "src/math/bits",
    "src/go/types",
    "src/mime/quotedprintable",
    "src/go/doc",
    "src/bytes",
    "src/sync/atomic",
    "src/encoding/base32",
    "src/net/url",
    "src/cmd/go/internal/modfetch/codehost",
    "src/container/list",
    "src/runtime/race",
    "src/os/user",
    "src/go/token",
    "src/archive/zip",
    "src/net/http/cgi",
    "src/internal/poll",
    "src/go/scanner",
    "src/net",
    "src/encoding/gob",
    "src/cmd/go/internal/modcmd",
    "src/sync",
    "src/embed",
    "src/runtime/cgo",
    "src/context",
    "src/crypto",
    "src/text/template",
    "src/crypto/x509",
    "src/testing",
    "src/cmd/go/internal/modget",
    "src/cmd/go/internal/modfetch",
    "src/cmd/go/internal/work",
    "src/encoding/ascii85",
    "src/math",
    "src/go/internal/gccgoimporter",
    "src/go/internal/gcimporter",
    "src/html/template",
    "src/cmd/go/internal/generate",
    "src/syscall",
    "src/internal/unsafeheader",
    "src/cmd/go/internal/fsys",
    "src/cmd/compile/internal/types2",
    "src/reflect",
    "src/encoding/base64",
    "src/debug/gosym",
    "src/net/http/httputil",
    "src/go/constant",
    "src/internal/reflectlite",
    "src/internal/fmtsort",
    "src/encoding/asn1",
    "src/syscall/js",
    "src/cmd/fix",
    "src/internal/lazytemplate",
    "src/encoding/xml",
    "src/net/http",
    "src/internal/syscall/windows/registry",
    "src/cmd/internal/buildid",
    "src/os",
    "src/cmd/go/internal/list",
    "src/embed/internal/embedtest",
    "src/database/sql",
    "src/runtime/debug",
    "src/cmd/go/internal/modload",
    "src/archive/tar",
    "src/builtin",
    "src/runtime/trace",
    "src/errors",
    "src/io",
    "src/log",
    "src/database/sql/driver",
    "src/debug/plan9obj",
    "src/debug/elf",
    "src/plugin",
    "src/encoding/json",
    "src/text/scanner",
    "src/crypto/tls",
    "src/cmd/go/internal/cmdflag",
    "src/testing/fstest",
    "src/go/internal/gcimporter/testdata",
    "src/math/rand",
    "src/cmd/go/internal/vcs",
    "src/net/rpc/jsonrpc",
    "src/runtime",
    "src/cmd/pack",
    "src/cmd/pprof",
    "src/sort",
    "src/internal/trace",
    "src/strings"
  ],
  "39351": [
    "src/sync/atomic",
    "src/expvar"
  ],
  "46293": [
    "src/cmd/compile/internal/test",
    "src/reflect"
  ],
  "46336": [
    "src/cmd/fix",
    "src/crypto/x509",
    "src/cmd/compile/internal/base",
    "src/html/template",
    "src/cmd/dist",
    "src/cmd/cgo",
    "src/go/build",
    "src/go/constant",
    "src/go/importer",
    "src/encoding/asn1",
    "src/encoding/xml",
    "src/net/http",
    "src/os",
    "src/runtime/debug",
    "src/cmd/go/internal/modload",
    "src/archive/tar",
    "src/encoding/json",
    "src/cmd/go/internal/cmdflag",
    "src/go/types",
    "src/cmd/compile/internal/ssa",
    "src/cmd/vendor/golang.org/x/arch/ppc64/ppc64asm",
    "src/regexp",
    "src/mime",
    "src/os/user",
    "src/runtime/pprof",
    "src/net/smtp",
    "src/crypto/ecdsa",
    "src/go/printer",
    "src/net/mail",
    "src/os/exec",
    "src/cmd/doc",
    "src/go/doc",
    "src/net/url",
    "src/net/http/cgi",
    "src/net"
  ],
  "42100": [
    "src/cmd/dist",
    "misc/ios",
    "src/runtime",
    "src/cmd/link/internal/ld",
    "src/runtime/cgo"
  ],
  "42681": [
    "src/cmd/go/internal/work",
    "src/cmd/dist",
    "test/fixedbugs",
    "src/internal/cfg"
  ],
  "48187": [
    "src/cmd/go/internal/version",
    "src/debug/buildinfo",
    "src/cmd/go/testdata/script",
    "src/cmd/go"
  ],
  "40276": [
    "src/cmd/go/testdata/mod",
    "src/cmd/go/testdata/script",
    "src/cmd/go/internal/modload",
    "src/cmd/go"
  ],
  "52221": [
    "src/crypto/x509",
    "src/go/build",
    "src/crypto/tls",
    "src/crypto/ecdh",
    "src/vendor",
    "src/crypto/elliptic",
    "src/crypto/ecdsa"
  ],
  "50332": [
    "src/cmd/go/testdata/script",
    "src/cmd/doc",
    "src/cmd/go/internal/workcmd",
    "src/cmd/go/internal/modcmd",
    "src/cmd/go/internal/work",
    "src/cmd/go/internal/version",
    "src/cmd/go",
    "src/cmd/go/internal/envcmd",
    "src/cmd/go/internal/bug",
    "src/cmd/go/internal/fmtcmd",
    "src/cmd/go/internal/tool",
    "src/cmd/go/internal/base"
  ],
  "42026": [
    "src/image/gif",
    "src/cmd/go/internal/cfg",
    "src/runtime/testdata/testprog",
    "src/compress/flate",
    "src/net/http",
    "src/os",
    "src/embed/internal/embedtest",
    "src/runtime/debug",
    "src/cmd/go/internal/modload",
    "src/io/ioutil",
    "src/archive/tar",
    "src/compress/lzw",
    "src/cmd/go",
    "src/runtime/trace",
    "src/cmd/cover",
    "src/cmd/trace",
    "src/cmd/go/internal/cache",
    "src/internal/obscuretestdata",
    "src/cmd/go/internal/bug",
    "src/crypto/tls",
    "src/math/bits",
    "src/go/types",
    "src/cmd/go/internal/vcs",
    "src/path/filepath",
    "src/runtime",
    "src/mime/multipart",
    "src/compress/zlib",
    "src/cmd/pack",
    "src/cmd/go/internal/auth",
    "src/runtime/race/testdata",
    "src/os/user",
    "src/cmd/go/internal/web",
    "src/runtime/pprof",
    "src/debug/pe",
    "src/cmd/go/internal/load",
    "src/go/internal/srcimporter",
    "src/debug/dwarf",
    "src/internal/cpu",
    "src/go/printer",
    "src/time",
    "src/cmd/go/internal/envcmd",
    "src/go/parser",
    "src/math/big",
    "src/go/format",
    "src/cmd/nm",
    "src/index/suffixarray",
    "src/os/exec",
    "src/cmd/go/testdata",
    "src/cmd/go/testdata/script",
    "src/cmd/go/internal/lockedfile/internal/filelock",
    "src/go/doc",
    "src/cmd/go/internal/test",
    "src/cmd/gofmt",
    "src/cmd/vet",
    "src/image/color/palette",
    "src/hash/crc32",
    "src/cmd/go/internal/lockedfile",
    "src/cmd/go/internal/modfetch/codehost",
    "src/runtime/race",
    "src/log/syslog",
    "src/archive/zip",
    "src/internal/poll",
    "src/go/scanner",
    "src/net",
    "src/cmd/fix",
    "src/cmd/go/internal/modcmd",
    "src/text/template",
    "src/crypto/md5",
    "src/crypto/x509",
    "src/testing",
    "src/compress/bzip2",
    "src/internal/testenv",
    "src/cmd/go/internal/modfetch",
    "src/cmd/go/internal/work",
    "src/cmd/go/internal/modfetch/zip_sum_test",
    "src/runtime/testdata/testprogcgo",
    "src/go/internal/gccgoimporter",
    "src/go/internal/gcimporter",
    "src/html/template",
    "src/syscall",
    "src/cmd/go/internal/generate",
    "src/os/signal",
    "src/go/build",
    "src/cmd/go/internal/clean",
    "src/image/internal/imageutil",
    "src/cmd/go/internal/fsys",
    "src/cmd/objdump",
    "src/cmd/go/internal/imports",
    "src/image/jpeg",
    "src/debug/gosym",
    "src/image/png",
    "src/go/importer",
    "src/strconv"
  ],
  "41184": [
    "src/sync",
    "src/runtime/cgo",
    "src/crypto/md5",
    "src/crypto/x509",
    "src/testing",
    "src/internal/testenv",
    "src/cmd/go/internal/modfetch",
    "src/cmd/go/internal/work",
    "src/go/format",
    "src/cmd/compile/internal/base",
    "src/math",
    "src/internal/abi",
    "src/go/build/constraint",
    "src/syscall",
    "src/os/signal",
    "src/internal/syscall/execenv",
    "src/go/build",
    "src/image/internal/imageutil",
    "src/cmd/go/internal/lockedfile/internal/filelock",
    "src/cmd/asm/internal/lex",
    "src/cmd/internal/obj",
    "src/internal/syscall/unix",
    "src/reflect",
    "src/cmd/internal/goobj",
    "src/cmd/go/internal/test",
    "misc/ios",
    "src/internal/bytealg",
    "src/internal/poll",
    "src/strconv",
    "src/cmd/fix",
    "src/net/http",
    "src/os",
    "src/net/internal/socktest",
    "src/internal/syscall/windows/sysdll",
    "src/cmd/vet/testdata/buildtag",
    "src/cmd/vendor/golang.org/x/tools/go/analysis/passes/buildtag",
    "src/cmd/vet/testdata/tagtest",
    "src/runtime/debug",
    "src/cmd/go/internal/modload",
    "src/archive/tar",
    "src/cmd/compile/internal/ir",
    "src/cmd/go",
    "src/internal/goroot",
    "src/crypto/sha1",
    "src/cmd/dist",
    "src/plugin",
    "src/crypto/tls",
    "misc/cgo/gmp",
    "src/math/rand",
    "src/cmd/link",
    "src/cmd/compile/internal/ssa",
    "src/cmd/pprof",
    "src/syscall/js",
    "src/regexp",
    "src/math/cmplx",
    "src/internal/syscall/windows/registry",
    "src/cmd/vendor/golang.org/x/sys/unix",
    "src/cmd/go/internal/web",
    "src/internal/syscall/windows",
    "src/runtime/pprof",
    "src/cmd/go/internal/load",
    "src/debug/pe",
    "src/cmd/link/internal/ld",
    "src/internal/cpu",
    "src/go/printer",
    "src/cmd/vendor/golang.org/x/tools/go/analysis/passes/loopclosure",
    "src/internal/race",
    "src/go/printer/testdata",
    "src/time",
    "src/cmd/compile/internal/typecheck",
    "src/math/big",
    "src/cmd/vet/testdata/asm",
    "src/cmd/go/internal/fix",
    "src/index/suffixarray",
    "src/cmd/go/internal/base",
    "src/os/exec",
    "src/math/bits",
    "src/cmd/asm/internal/asm",
    "src/path/filepath",
    "src/go/types",
    "src/runtime",
    "src/go/doc",
    "src/bytes",
    "src/sync/atomic",
    "src/cmd/vendor/golang.org/x/tools/go/analysis",
    "src/cmd/vet",
    "src/image/color/palette",
    "src/hash/crc32",
    "src/cmd/go/internal/lockedfile",
    "api",
    "src/cmd/go/internal/modfetch/codehost",
    "src/runtime/race",
    "src/os/user",
    "src/log/syslog",
    "src/net",
    "src/encoding/gob"
  ],
  "43401": [
    "src/encoding/csv"
  ],
  "47164": [
    "src/log"
  ],
  "40728": [
    "src/cmd/go/internal/modget",
    "src/cmd/go/internal/work",
    "src/cmd/go/internal/modload",
    "src/cmd/go/internal/fmtcmd",
    "src/cmd/go/testdata/mod",
    "src/cmd/go/internal/modfetch",
    "src/cmd/go/internal/base",
    "src/cmd/go/testdata/script",
    "src/cmd/go/internal/modcmd"
  ],
  "47609": [
    "src/unicode/utf8",
    "src/cmd/compile/internal/test"
  ],
  "48424": [
    "src/cmd/compile/internal/syntax",
    "src/go/printer/testdata",
    "test/typeparam",
    "src/go/types",
    "src/go/parser",
    "src/go/internal/gcimporter",
    "src/cmd/compile/internal/types2"
  ],
  "38248": [
    "src/syscall/js",
    "src/cmd/compile/internal/gc",
    "src/cmd/internal/obj/wasm",
    "src/cmd/internal/obj",
    "src/cmd/internal/goobj"
  ],
  "37033": [
    "src/cmd/cgo",
    "src/runtime/cgo",
    "src/cmd/link/internal/ld"
  ],
  "51868": [
    "api",
    "src/debug/pe"
  ],
  "51430": [
    "src/internal/coverage/calloc",
    "src/cmd/covdata/testdata",
    "src/cmd/dist",
    "src/cmd/covdata",
    "src/internal/coverage/cformat",
    "src/cmd/compile/internal/gc",
    "src/cmd/compile/internal/typecheck",
    "src/internal/coverage/encodecounter",
    "src/cmd/compile/internal/coverage",
    "src/cmd/internal/cov",
    "src/internal/coverage/decodecounter",
    "src/cmd/compile/internal/base",
    "src/internal/coverage/cmerge",
    "src/internal/coverage/pods",
    "src/internal/coverage/test",
    "src/internal/coverage/stringtab"
  ],
  "37023": [
    "src/runtime",
    "src/runtime/debug"
  ],
  "48256": [
    "src/cmd/go/testdata/script",
    "src/cmd/go",
    "src/cmd/go/internal/workcmd",
    "src/cmd/go/internal/modcmd"
  ],
  "47651": [
    "src/encoding/gob",
    "src/text/template",
    "src/html/template",
    "test/fixedbugs/issue32901.dir",
    "src/reflect",
    "src/cmd/gofmt",
    "src/internal/reflectlite",
    "test",
    "src/internal/fmtsort",
    "src/encoding/asn1",
    "src/cmd/fix",
    "src/encoding/xml",
    "src/database/sql",
    "src/database/sql/driver",
    "src/encoding/json",
    "src/net/rpc",
    "src/testing/quick",
    "src/fmt",
    "src/go/ast",
    "src/flag",
    "src/encoding/binary"
  ],
  "46121": [
    "src/html/template",
    "api"
  ],
  "51644": [
    "src/encoding/binary"
  ],
  "45453": [
    "test/codegen",
    "src/cmd/go/internal/work",
    "src/cmd/dist",
    "src/cmd/go/internal/cfg",
    "src/cmd/compile/internal/amd64",
    "src/internal/buildcfg",
    "src/runtime",
    "src/cmd/compile/internal/ssa",
    "src/internal/cfg"
  ],
  "46059": [
    "src/net/url"
  ],
  "53003": [
    "src/cmd/compile/internal/ir",
    "src/go/types",
    "src/cmd/compile/internal/ssagen",
    "src/cmd/compile/internal/escape",
    "src/cmd/compile/internal/typecheck",
    "src/cmd/compile/internal/walk",
    "src/cmd/compile/internal/types2",
    "src/unsafe",
    "test"
  ],
  "29770": [
    "src/text/template",
    "src/html/template",
    "src/text/template/parse"
  ],
  "43931": [
    ".",
    "src/cmd/compile/internal/staticdata",
    "src/embed/internal/embedtest",
    "src/cmd/compile/internal/noder",
    "src/go/types"
  ],
  "39557": [
    "src/flag"
  ],
  "48294": [
    "src/reflect"
  ],
  "46731": [
    "src/cmd/compile/internal/noder",
    "test/fixedbugs",
    "src/cmd/compile/internal/ir",
    "src/cmd/compile/internal/typecheck",
    "src/runtime",
    "src/cmd/compile/internal/typebits",
    "src/cmd/cgo",
    "src/reflect",
    "test"
  ],
  "43620": [
    "src/testing"
  ],
  "37519": [
    "src/cmd/go/testdata/script",
    "src/cmd/go/internal/modget",
    "src/cmd/go/internal/modfetch",
    "src/cmd/go",
    "src/cmd/go/internal/web",
    "src/cmd/go/internal/help"
  ],
  "34527": [
    "src/internal/cfg",
    "src/cmd/go/internal/modfetch",
    "src/cmd/go/internal/clean",
    "src/cmd/go/testdata/script",
    "src/cmd/go/internal/modfetch/codehost",
    "src/cmd/go/internal/cfg",
    "src/cmd/go/internal/modload"
  ],
  "52792": [
    "src/cmd/go/internal/modfetch",
    "src/cmd/go/testdata/script",
    "src/cmd/go/internal/modinfo",
    "src/cmd/go/internal/list",
    "src/cmd/go/internal/modload",
    "src/cmd/go"
  ],
  "44435": [
    "src/cmd/go/internal/modcmd",
    "src/cmd/go",
    "src/cmd/go/internal/modload",
    "src/cmd/go/testdata/script"
  ],
  "47916": [
    "src/go/types",
    "src/cmd/compile/internal/noder",
    "src/cmd/compile/internal/types2"
  ],
  "40592": [
    "src/reflect",
    "src/encoding/json"
  ],
  "46287": [
    "src/crypto/x509",
    "src/crypto/x509/internal/macos"
  ],
  "51566": [
    "src/net/http",
    "src/io"
  ],
  "41696": [
    "src/cmd/go",
    "src/cmd/link",
    "src/cmd/go/testdata/script",
    "src/cmd/go/internal/work",
    "src/cmd/go/internal/test",
    "src/cmd/go/internal/cfg"
  ],
  "41730": [
    "src/internal/cfg",
    "src/cmd/go/internal/modcmd",
    "src/cmd/go/internal/modget",
    "src/cmd/go/internal/modfetch",
    "src/cmd/go/internal/work",
    "src/cmd/go/testdata/script",
    "src/cmd/go/internal/cfg",
    "src/cmd/go/internal/list",
    "src/cmd/go/internal/modload",
    "src/cmd/go",
    "src/cmd/go/internal/vcs",
    "src/cmd/go/internal/help",
    "src/cmd/go/internal/envcmd"
  ],
  "48218": [
    "src/reflect"
  ],
  "40481": [
    "src/cmd/compile/internal/ssagen",
    "test",
    "src/cmd/compile/internal/walk",
    "doc",
    "src/unsafe",
    "src/cmd/compile/internal/typecheck",
    "src/go/types"
  ],
  "43947": [
    "src/cmd/go/testdata/script",
    "src/cmd/dist",
    "src/os/exec"
  ],
  "47257": [
    "src/cmd/go/internal/load",
    "src/go/types",
    "src/cmd/go/internal/modindex",
    "src/cmd/go/testdata/script",
    "src/crypto/x509/internal/macOS",
    "src/crypto/x509",
    "src/cmd/go/internal/work",
    "src/cmd/go",
    "src/cmd/compile/internal/types2"
  ],
  "43698": [
    "src/embed/internal/embedtest",
    "src/embed"
  ],
  "41563": [
    "src/text/template",
    "src/encoding/asn1",
    "src/encoding/xml",
    "src/net/rpc",
    "src/encoding/json",
    "src/reflect"
  ],
  "50599": [
    "src/cmd/go/internal/work",
    "src/go/build",
    "src/cmd/internal/moddeps",
    "src/os/exec"
  ],
  "34652": [
    "src/text/template",
    "src/html/template",
    "src/text/template/parse"
  ],
  "32406": [
    "src/crypto/tls",
    "src/net/http"
  ],
  "52463": [
    "src/go/parser",
    "api",
    "src/go/ast"
  ],
  "35562": [
    "src/net/http"
  ],
  "46746": [
    "api",
    "src/reflect"
  ],
  "37196": [
    "src/cmd/compile/internal/walk",
    "src/cmd/compile/internal/typecheck/_builtin",
    "doc",
    "src/runtime",
    "src/cmd/compile/internal/ssagen",
    "src/time"
  ],
  "45454": [
    "src/internal/buildcfg",
    "src/cmd/go/testdata/script",
    "src/go/build",
    "src/cmd/go/internal/cfg"
  ],
  "41066": [
    "src/crypto/tls"
  ],
  "28308": [
    "src/cmd/go/internal/test",
    "src/cmd/vet",
    "src/cmd/vendor/golang.org/x/tools/go/analysis/passes/copylock",
    "src/net/http",
    "src",
    "src/cmd/vendor/golang.org/x/tools/go/types/typeutil",
    "src/cmd/vendor/golang.org/x/tools/go/analysis/passes/structtag",
    "src/cmd/vendor/golang.org/x/tools/internal/stdlib",
    "src/vendor/golang.org/x/crypto/internal/poly1305",
    "src/cmd/vendor",
    "src/cmd/vendor/golang.org/x/tools/go/analysis/passes/lostcancel",
    "src/cmd/vendor/golang.org/x/tools/internal/typesinternal",
    "src/cmd/vendor/golang.org/x/tools/internal/astutil/cursor",
    "src/cmd/vendor/golang.org/x/tools/internal/typesinternal/typeindex",
    "src/cmd/vet/testdata/hostport",
    "src/cmd/vendor/golang.org/x/sys/unix",
    "src/vendor/golang.org/x/crypto/cryptobyte",
    "src/cmd/vendor/golang.org/x/tools/go/analysis/passes/nilfunc",
    "src/cmd/vendor/golang.org/x/sync/errgroup",
    "src/vendor",
    "src/cmd/vendor/golang.org/x/tools/go/analysis/passes/unreachable",
    "src/cmd/vendor/golang.org/x/tools/internal/bisect",
    "src/cmd/vendor/golang.org/x/tools/internal/typeparams",
    "src/cmd/vendor/golang.org/x/tools/internal/astutil",
    "src/cmd/vendor/golang.org/x/tools/go/analysis/passes/testinggoroutine",
    "src/cmd/vendor/golang.org/x/tools/go/analysis/passes/hostport",
    "src/cmd/vendor/golang.org/x/tools/internal/analysisinternal",
    "src/cmd",
    "src/vendor/golang.org/x/sys/cpu",
    "src/cmd/vendor/golang.org/x/tools/go/analysis/passes/composite",
    "src/cmd/vendor/golang.org/x/sys/windows",
    "src/cmd/vendor/golang.org/x/tools/internal/analysisinternal/typeindex"
  ],
  "48257": [
    "src/cmd/go/testdata/script",
    "src/cmd/go/internal/workcmd"
  ],
  "38781": [
    "src/net/http",
    "src/testing/iotest"
  ],
  "43823": [
    "src/time"
  ],
  "49390": [
    "src/cmd/dist",
    "src/internal/testenv"
  ],
  "53021": [
    "src/crypto/subtle",
    "src/crypto/cipher"
  ],
  "35833": [
    "src/crypto/x509",
    "src/crypto/elliptic",
    "src/math/big",
    "src/crypto/rsa"
  ],
  "40255": [
    "src/runtime",
    "src/cmd/go/internal/work",
    "src/cmd/asm/internal/asm",
    "src/reflect",
    "src",
    "src/cmd/go",
    "src/cmd/dist",
    "src/cmd/compile/internal/ssa",
    "src/cmd/compile/internal/x86",
    "src/cmd/go/internal/help"
  ],
  "45754": [
    "src/flag",
    "src/go/build"
  ],
  "42088": [
    "src/cmd/go/internal/load",
    "src/cmd/go/testdata/script",
    "src/cmd/go/testdata/mod",
    "src/cmd/go/internal/work",
    "src/cmd/go",
    "src/cmd/go/internal/run"
  ],
  "53002": [
    "src/net/http/httputil"
  ],
  "53482": [
    "src/net"
  ],
  "44011": [
    "src/os",
    "src/os/exec",
    "src/syscall"
  ],
  "46485": [
    "src/cmd/go/internal/load",
    "src/go/internal/srcimporter",
    "src/cmd/cgo",
    "src/cmd/gofmt"
  ],
  "50101": [
    "src/net",
    "src/internal/syscall/unix"
  ],
  "40995": [
    "src/cmd/vendor/golang.org/x/sys/unix",
    "src/cmd/link/internal/mips64",
    "src/runtime",
    "src/vendor/golang.org/x/sys/cpu",
    "src/cmd/vendor/golang.org/x/sys/windows",
    "src/syscall",
    "src/cmd/dist"
  ],
  "42027": [
    "src/cmd/go/internal/modfetch",
    "src/go/build",
    "src/cmd/go/internal/version",
    "test",
    "src/cmd/fix",
    "src/compress/gzip",
    "src/cmd/go",
    "src/io/fs",
    "src/index/suffixarray",
    "src/cmd/go/testdata",
    "src/path/filepath",
    "src/go/doc",
    "src/cmd/gofmt"
  ],
  "40357": [
    "src/cmd/go/internal/list",
    "src/cmd/go/internal/modload",
    "src/cmd/go/internal/modcmd"
  ],
  "45973": [
    "src/net/http"
  ],
  "47342": [
    "src/cmd/dist",
    "src/go/build",
    "src/hash/maphash"
  ],
  "33920": [
    "src/io/ioutil"
  ],
  "46518": [
    "src/strings",
    "src/net/netip",
    "src/net",
    "src/bytes",
    "src/net/http"
  ],
  "37168": [
    "src/crypto/rc4",
    "src/image"
  ],
  "50859": [
    "src/runtime",
    "src/sync/atomic",
    "src/sync",
    "doc"
  ],
  "47216": [
    "src/runtime",
    "src/runtime/metrics"
  ],
  "49097": [
    "src/net"
  ],
  "37475": [
    "src/go/build",
    "src/cmd/go/internal/version",
    "src/runtime/debug",
    "src/cmd/go/internal/modload",
    "src/cmd/go/internal/vcs",
    "src/debug/buildinfo",
    "src/cmd/go/internal/load",
    "src/cmd/go/testdata/script"
  ],
  "35998": [
    "src/io/ioutil",
    "src/testing"
  ],
  "42710": [
    "src/hash/maphash"
  ],
  "27628": [
    "src/cmd/go/internal/cache",
    "src/cmd/go/testdata/script",
    "src/cmd/go/internal/work"
  ],
  "51684": [
    "src/regexp/syntax"
  ],
  "41048": [
    "src/net/http"
  ],
  "45430": [
    "src/crypto/tls",
    "src/crypto/tls/testdata"
  ],
  "30999": [
    "src/net/testdata",
    "src/net"
  ],
  "46308": [
    "src/crypto/tls"
  ],
  "46552": [
    "src/syscall",
    "src/runtime"
  ],
  "44006": [
    "src/syscall/js"
  ],
  "51914": [
    "src/net/http/httputil"
  ],
  "47209": [
    "src/cmd/go/internal/fsys",
    "src/path/filepath",
    "src/io/fs"
  ],
  "38776": [
    "src/crypto/sha256",
    "src/crypto/sha512",
    "src/crypto/hmac"
  ],
  "51682": [
    "src/cmd/compile/internal/types2",
    "src/go/types"
  ],
  "45963": [
    "src/cmd/go/testdata/script",
    "src/cmd/go/internal/test",
    "src/cmd/go"
  ],
  "39214": [
    "src/strings",
    "src/internal/cpu",
    "src/cmd/compile/internal/types",
    "src/testing",
    "src/cmd/internal/obj",
    "src/strconv"
  ],
  "44221": [
    "src/encoding/csv"
  ],
  "37112": [
    "src/cmd/go/internal/work",
    "src/runtime/metrics",
    "src/go/build",
    "src/runtime"
  ],
  "33184": [
    "src/runtime",
    "src/time"
  ],
  "48409": [
    "src/runtime/metrics",
    "src/runtime/testdata/testprog",
    "src/runtime/debug",
    "src/runtime"
  ],
  "41773": [
    "src/net/http"
  ],
  "40356": [
    "src/cmd/vendor/golang.org/x/tools/go/analysis/passes/sigchanyzer",
    "src/cmd/vendor/golang.org/x/tools/go/analysis/passes/stdmethods"
  ],
  "52746": [
    "src/cmd/go/internal/modfetch/codehost",
    "src/cmd/go/internal/vcs",
    "src/time"
  ],
  "33136": [
    "src/reflect"
  ],
  "39444": [
    "src/os"
  ],
  "39034": [
    "src/time"
  ],
  "48367": [
    "src/strings",
    "src/bytes"
  ],
  "40025": [
    "src/os",
    "src/io/ioutil",
    "src/io"
  ],
  "50792": [
    "test/typeparam/issue50121b.dir",
    "test/typeparam/issue50121.dir",
    "test/typeparam",
    "api"
  ],
  "48530": [
    "src/net"
  ],
  "50770": [
    "src/time"
  ],
  "36771": [
    "src/strconv"
  ],
  "51972": [
    "src/sync"
  ],
  "40082": [
    "src/database/sql"
  ],
  "38017": [
    "src/time/tzdata",
    "src/time",
    "src/go/build"
  ],
  "45729": [
    "src/net"
  ],
  "48157": [
    "src/runtime",
    "src/internal/testenv",
    "src/internal/fuzz",
    "src/cmd/go/testdata/script"
  ],
  "44940": [
    "src/unicode/utf16"
  ],
  "43744": [
    "src/time",
    "src/runtime"
  ],
  "43724": [
    "src/syscall",
    "src/internal/syscall/windows/registry",
    "src/internal/syscall/windows"
  ],
  "45899": [
    "src/io"
  ],
  "42102": [
    "src/time",
    "api"
  ],
  "51225": [
    "src/cmd/compile"
  ],
  "37776": [
    "src/net/url"
  ],
  "38687": [
    "src/cmd/go/testdata/script",
    "src/cmd/go/internal/generate",
    "src/cmd/go"
  ],
  "29062": [
    "src/cmd/go/testdata/script",
    "src/cmd/go/internal/test"
  ],
  "44505": [
    "src/sort",
    "src",
    "src/cmd/dist"
  ],
  "44167": [
    "src/runtime",
    "src/internal/goexperiment"
  ],
  "50601": [
    "src/encoding/binary"
  ],
  "44815": [
    "src/bufio"
  ],
  "50674": [
    "src/crypto/x509/pkix",
    "src/crypto/x509"
  ],
  "19367": [
    "src/runtime"
  ],
  "43602": [
    "src/embed"
  ],
  "53466": [
    "src/syscall",
    "src/cmd/dist",
    "src/cmd/link/internal/riscv64",
    "src/runtime",
    "src/cmd/link/internal/ld"
  ],
  "47658": [
    "src/cmd/compile/internal/test",
    "src/reflect"
  ],
  "21865": [
    "src/crypto/rc4"
  ],
  "40337": [
    "src/crypto/dsa",
    "src/crypto/x509"
  ],
  "39178": [
    "src/net"
  ],
  "48152": [
    "src/crypto/tls",
    "src/net/http"
  ],
  "41792": [
    "src/flag"
  ],
  "28089": [
    "src/go/ast",
    "src/cmd/go"
  ],
  "50860": [
    "src/cmd/compile/internal/escape",
    "src/cmd/compile/internal/test",
    "src/sync/atomic"
  ],
  "46258": [
    "src/syscall"
  ],
  "45428": [
    "src/crypto/tls"
  ],
  "44808": [
    "src/image",
    "api",
    "src/image/draw"
  ],
  "50842": [
    "src/io"
  ],
  "48801": [
    "src/cmd/vendor",
    "src/cmd/vendor/golang.org/x/tools/go/analysis/passes/timeformat",
    "src/cmd/vet"
  ],
  "39904": [
    "src/testing"
  ],
  "34626": [
    "src/testing"
  ],
  "26535": [
    "src/compress/lzw"
  ],
  "41682": [
    "src/crypto/x509"
  ],
  "48866": [
    "src/mime"
  ],
  "44143": [
    "src/crypto/tls"
  ],
  "39567": [
    "src/net/http"
  ],
  "51414": [
    "src/time"
  ],
  "51777": [
    "src/net/netip"
  ],
  "52376": [
    "src/reflect"
  ],
  "42322": [
    "src/os",
    "src/embed/internal/embedtest",
    "src/testing/fstest",
    "src/io/fs"
  ],
  "41790": [
    "src/database/sql"
  ],
  "32779": [
    "src/encoding/json"
  ],
  "49580": [
    "src/archive/tar",
    "src/testing/fstest",
    "src/os",
    "src/io/fs"
  ],
  "50429": [
    "src/go/parser",
    "src/go/ast"
  ],
  "45435": [
    "src/sync"
  ],
  "53573": [
    "src/crypto/x509"
  ],
  "48052": [
    "src/debug/plan9obj"
  ],
  "41260": [
    "src/testing",
    "api"
  ],
  "51668": [
    "src/fmt"
  ],
  "45964": [
    "src/syscall"
  ],
  "45100": [
    "src/net/url"
  ],
  "53200": [
    "src/go/token"
  ],
  "37255": [
    "src/os/signal"
  ],
  "45033": [
    "src/strconv"
  ],
  "52444": [
    "src/crypto/x509"
  ],
  "50489": [
    "src/math/big"
  ],
  "37974": [
    "src/go/ast"
  ],
  "53346": [
    "src/encoding/xml"
  ],
  "47066": [
    "src/reflect"
  ],
  "32716": [
    "src/crypto/tls"
  ],
  "39057": [
    "src/log"
  ],
  "35804": [
    "src/database/sql"
  ],
  "46259": [
    "src/syscall"
  ],
  "38079": [
    "src/net/http/httputil"
  ],
  "46279": [
    "src/cmd/link/internal/ld"
  ],
  "53747": [
    "src/flag"
  ],
  "46131": [
    "src/reflect"
  ],
  "46057": [
    "src/crypto/x509"
  ],
  "31804": [
    "src/crypto/ed25519"
  ],
  "50102": [
    "api",
    "src/archive/tar"
  ],
  "40962": [
    "src/io"
  ],
  "41196": [
    "src/cmd/go"
  ],
  "47142": [
    "src/database/sql",
    "src/database/sql/driver"
  ],
  "50436": [
    "src/os/exec"
  ],
  "43993": [
    "src/text/template"
  ],
  "44196": [
    "src/time"
  ],
  "37533": [
    "src/flag"
  ],
  "42387": [
    "src/io/fs"
  ],
  "46771": [
    "src/mime/multipart"
  ],
  "35044": [
    "src/crypto/x509"
  ],
  "30715": [
    "src/net/http"
  ],
  "45628": [
    "src/encoding/xml"
  ],
  "46648": [
    "src/go/types"
  ],
  "42782": [
    "src/reflect"
  ],
  "50062": [
    "src/time"
  ],
  "47527": [
    "src/bufio"
  ],
  "51896": [
    "src/unicode/utf16"
  ],
  "51428": [
    "src/net"
  ],
  "50465": [
    "src/net/http/httputil"
  ],
  "49471": [
    "src/runtime"
  ],
  "47005": [
    "src/net/url"
  ]
}